{
    "Data": [
        {
            "Name":"Данные открытые ",
            "Id": "1checkboxgroup1",
            "Show": true,
            "Sections": [
                {
                    "Name": "Сведения",
                    "Link": ""
                },
                {
                    "Name": "Сведения длинное название",
                    "Link": ""
                },
                {
                    "Name": "Сведения длинное название",
                    "Link": ""
                },
                {
                    "Name": "Сведения длинное название",
                    "Link": ""
                },
                {
                    "Name": "Сведения очень длинное название уместилось в три строки",
                    "Link": ""
                },
                {
                    "Name": "Сведения очень длинное название уместилось в три строки",
                    "Link": ""
                },
                {
                    "Name": "Сведения очень длинное название уместилось в три строки",
                    "Link": ""
                }
            ]
        },
        {
            "Name":"2 Данные",
            "Id": "1checkboxgroup2",
            "Show": false,
            "Sections": [
                {
                    "Name": "Сведения",
                    "Link": ""
                },
                {
                    "Name": "Сведения длинное название",
                    "Link": ""
                },
                {
                    "Name": "Сведения длинное название",
                    "Link": ""
                },
                {
                    "Name": "Сведения длинное название",
                    "Link": ""
                },
                {
                    "Name": "Сведения очень длинное название уместилось в три строки",
                    "Link": ""
                },
                {
                    "Name": "Сведения очень длинное название уместилось в три строки",
                    "Link": ""
                },
                {
                    "Name": "Сведения очень длинное название уместилось в три строки",
                    "Link": ""
                }
            ]
        },
        {
            "Name":"3 Данные",
            "Id": "1checkboxgroup3",
            "Show": false,
            "Sections": [
                {
                    "Name": "Сведения",
                    "Link": ""
                },
                {
                    "Name": "Сведения длинное название",
                    "Link": ""
                },
                {
                    "Name": "Сведения длинное название",
                    "Link": ""
                },
                {
                    "Name": "Сведения длинное название",
                    "Link": ""
                },
                {
                    "Name": "Сведения очень длинное название уместилось в три строки",
                    "Link": ""
                },
                {
                    "Name": "Сведения очень длинное название уместилось в три строки",
                    "Link": ""
                },
                {
                    "Name": "Сведения очень длинное название уместилось в три строки",
                    "Link": ""
                }
            ]
        }
    ]
  }